gwapi/__init__.py
gwapi/auth.py
gwapi/data.py
gwapi_genwch-0.0.4.dist-info/LICENSE
gwapi_genwch-0.0.4.dist-info/METADATA
gwapi_genwch-0.0.4.dist-info/WHEEL
gwapi_genwch-0.0.4.dist-info/top_level.txt
gwapi_genwch-0.0.4.dist-info/RECORD
