Metadata-Version: 2.1
Name: gwapi-genwch
Version: 0.0.4
Summary: gwapi
Home-page: https://github.com/genwch/gwapi
Author: genwch
Author-email: 
License: UNKNOWN
Platform: UNKNOWN
Classifier: Programming Language :: Python :: 3
Classifier: License :: OSI Approved :: MIT License
Classifier: Operating System :: OS Independent
Requires-Python: >=3.7
Requires-Dist: gwcomm-genwch
Requires-Dist: requests
